colorcompass/__init__.py
colorcompass/color_compass.py
colorcompass/color_dictionary.py
colorcompass-1.2.3.dist-info/LICENSE.md
colorcompass-1.2.3.dist-info/METADATA
colorcompass-1.2.3.dist-info/WHEEL
colorcompass-1.2.3.dist-info/top_level.txt
colorcompass-1.2.3.dist-info/RECORD
